slackrobot-0.1.3.dist-info/DESCRIPTION.rst
slackrobot-0.1.3.dist-info/METADATA
slackrobot-0.1.3.dist-info/top_level.txt
slackrobot-0.1.3.dist-info/metadata.json
slackrobot-0.1.3.dist-info/WHEEL
slackrobot-0.1.3.dist-info/RECORD
slackrobot/__init__.py
slackrobot/utils/thread.py
slackrobot/utils/__init__.py
slackrobot/utils/plugins.py
