Metadata-Version: 2.0
Name: slackrobot
Version: 0.1.3
Summary: Simple python implementation of slack bot
Home-page: https://github.com/traveloka/python-slackrobot
Author: Ricky Winata
Author-email: ricky.w12@gmail.com
License: MIT
Keywords: slack bot robot
Platform: UNKNOWN
Requires-Dist: slackclient
